ddgr.py
ddgr-2.1.dist-info/LICENSE
ddgr-2.1.dist-info/METADATA
ddgr-2.1.dist-info/WHEEL
ddgr-2.1.dist-info/entry_points.txt
ddgr-2.1.dist-info/top_level.txt
ddgr-2.1.dist-info/RECORD
